enaCLI/__init__.py
enaCLI/__main__.py
enaCLI/main.py
enaCLI/others/XMLGenerator.py
enaCLI/others/__init__.py
enaCLI/packages/XMLGenerator.py
enaCLI/packages/__init__.py
enaCLI/packages/antibiogram.py
enaCLI/packages/antibiotics.txt
enaCLI/packages/submission.py
enaCLI/packages/webin-cli-7.3.1.jar
enaCLI/packages/webin.py
enaCLI-1.0.8.dist-info/LICENSE
enaCLI-1.0.8.dist-info/METADATA
enaCLI-1.0.8.dist-info/WHEEL
enaCLI-1.0.8.dist-info/entry_points.txt
enaCLI-1.0.8.dist-info/top_level.txt
enaCLI-1.0.8.dist-info/RECORD
