Metadata-Version: 2.1
Name: enaCLI
Version: 1.0.8
Summary: This script facilitates the submission of projects, samples, runs, assemblies, and other analyses to the public repository ENA (European Nucleotide Archive). It also assists in validating AMR (Antimicrobial Resistance) antibiograms before submission.
Home-page: https://github.com/KhadimGueyeKgy1/enaCLI
Author: Khadim GUEYE, Colman O'Cathail , Zahra Waheed
Author-email: khadim@ebi.ac.uk, ocathail@ebi.ac.uk , zahra@ebi.ac.uk
Maintainer: Khadim GUEYE
License-File: LICENSE
Requires-Dist: argparse
Requires-Dist: Pandas3
Requires-Dist: lxml
Requires-Dist: openpyxl >=3.1.0
